{"GlobalPropertiesHash":"G9EVKiezrIQjLf38fQNRMeDu+7Jrj5OROZqYFdpNw/8=","FingerprintPatternsHash":"gq3WsqcKBUGTSNle7RKKyXRIwh7M8ccEqOqYvIzoM04=","PropertyOverridesHash":"8ZRc1sGeVrPBx4lD717BgRaQekyh78QKV9SKsdt638U=","InputHashes":["1S6IKpR0kVSu1OVs3Oju6pFYYz\u002Bntz5wyMtmdHpEtl0=","4PDpqHcFXT1\u002BWgCoDGu7KlEJxM9/XyD5eEQyoWyg6Xc=","MBEjCAVARTQ11izfihOhHFzthvFO6XrLfyUQg5wvQLA=","YL5xtGS5gZr8JT5RrWQFH0a\u002BVdiNl72RdgcY4O0D4LU=","FrJ500HtW8d20WHJ2AuF7s9DX6WU8QmaeZ694WD9yFI=","jol9pCvvUrFmiye5VXR1yE1nwRm3l/z09lHJiljQcpY=","/EAIyWEjyPMNE0023gZvVix4e4WetrEuOLpAPvdrrcs=","vYGUZurzmdcLI5OolzjN6AFV6EG38Uhjkvt8RSVlORQ=","Umvf1B434qdh8g4tn7PIB1JBVnPxwIVTu5R8Xz4d9LU=","ZsUtQYz2AL\u002BNcWGroWG\u002BhRYpX3TF1YCTztRFrewnGhU=","55hSJC/HRpexVqPMOKIOpjDSWYWJ0lkhktxahpsvjq0=","aj4eq4i5uRbqJeO3EXnBl9Sg0Me8G23tS\u002BB/Oc3hIFQ=","H1qLLArJfuqkgEuKVm6un8bjs1z01kHa9xF/5HvRGKM=","yrdlqzrHirfccHI2rzV9uUKClQH5YFciqlGfSo80KLM=","kW4/ere0b2vRaDdqvXMfl0LXVuYN\u002Bcxc1DuTQSuXX30="],"CachedAssets":{"1S6IKpR0kVSu1OVs3Oju6pFYYz\u002Bntz5wyMtmdHpEtl0=":{"Identity":"D:\\Documents\\GitHub\\GASCAR\\GASCAR.API\\wwwroot\\index.html","SourceId":"GASCAR.API","SourceType":"Discovered","ContentRoot":"D:\\Documents\\GitHub\\GASCAR\\GASCAR.API\\wwwroot\\","BasePath":"/","RelativePath":"index#[.{fingerprint}]?.html","AssetKind":"All","AssetMode":"All","AssetRole":"Primary","AssetMergeBehavior":null,"AssetMergeSource":"","RelatedAsset":null,"AssetTraitName":null,"AssetTraitValue":null,"Fingerprint":"5ipweew5fc","Integrity":"47DEQpj8HBSa\u002B/TImW\u002B5JCeuQeRkm5NMpJWZG3hSuFU=","CopyToOutputDirectory":"Never","CopyToPublishDirectory":"PreserveNewest","OriginalItemSpec":"wwwroot\\index.html","FileLength":0,"LastWriteTime":"2026-01-26T20:41:28.5319847+00:00"},"4PDpqHcFXT1\u002BWgCoDGu7KlEJxM9/XyD5eEQyoWyg6Xc=":{"Identity":"D:\\Documents\\GitHub\\GASCAR\\GASCAR.API\\wwwroot\\_framework","SourceId":"GASCAR.API","SourceType":"Discovered","ContentRoot":"D:\\Documents\\GitHub\\GASCAR\\GASCAR.API\\wwwroot\\","BasePath":"/","RelativePath":"_framework#[.{fingerprint}]?","AssetKind":"All","AssetMode":"All","AssetRole":"Primary","AssetMergeBehavior":null,"AssetMergeSource":"","RelatedAsset":null,"AssetTraitName":null,"AssetTraitValue":null,"Fingerprint":"5ipweew5fc","Integrity":"47DEQpj8HBSa\u002B/TImW\u002B5JCeuQeRkm5NMpJWZG3hSuFU=","CopyToOutputDirectory":"Never","CopyToPublishDirectory":"PreserveNewest","OriginalItemSpec":"wwwroot\\_framework","FileLength":0,"LastWriteTime":"2026-01-26T20:41:22.3932381+00:00"}},"CachedCopyCandidates":{}}